gucken/__init__.py
gucken/__main__.py
gucken/aniskip.py
gucken/custom_widgets.py
gucken/gucken.py
gucken/networking.py
gucken/packer.py
gucken/rome.py
gucken/settings.py
gucken/update.py
gucken/utils.py
gucken/hoster/__init__.py
gucken/hoster/_hosters.py
gucken/hoster/common.py
gucken/hoster/doodstream.py
gucken/hoster/filemoon.py
gucken/hoster/loadx.py
gucken/hoster/luluvdo.py
gucken/hoster/speedfiles.py
gucken/hoster/streamtape.py
gucken/hoster/veo.py
gucken/hoster/vidmoly.py
gucken/hoster/vidoza.py
gucken/player/__init__.py
gucken/player/_players.py
gucken/player/android.py
gucken/player/common.py
gucken/player/ffplay.py
gucken/player/flatpak.py
gucken/player/mpv.py
gucken/player/other.py
gucken/player/vlc.py
gucken/player/wmplayer.py
gucken/provider/__init__.py
gucken/provider/aniworld.py
gucken/provider/burningseries.py
gucken/provider/common.py
gucken/provider/crunchyroll.py
gucken/provider/serienstream.py
gucken/provider/streamcloud.py
gucken/resources/default_settings.toml
gucken/resources/gucken.css
gucken/resources/mpv_gucken.lua
gucken/resources/vlc_gucken.lua
gucken/tracker/__init__.py
gucken/tracker/anilist.py
gucken/tracker/aniworld.py
gucken/tracker/common.py
gucken/tracker/myanimelist.py
gucken/tracker/serienstream.py
gucken-0.3.9.dist-info/METADATA
gucken-0.3.9.dist-info/WHEEL
gucken-0.3.9.dist-info/entry_points.txt
gucken-0.3.9.dist-info/licenses/LICENSE.txt
gucken-0.3.9.dist-info/RECORD
