Metadata-Version: 2.4
Name: gucken
Version: 0.3.9
Summary: Gucken is a Terminal User Interface which allows you to browse and watch your favorite anime's with style.
Project-URL: Repository, https://github.com/Commandcracker/gucken
Author: Commandcracker
Maintainer: Commandcracker
License: MIT License
License-File: LICENSE.txt
Keywords: anime,gucken,serien,series,tui
Classifier: Development Status :: 2 - Pre-Alpha
Classifier: Environment :: Console
Classifier: Intended Audience :: Developers
Classifier: Intended Audience :: End Users/Desktop
Classifier: License :: OSI Approved :: MIT License
Classifier: Natural Language :: English
Classifier: Natural Language :: German
Classifier: Operating System :: Android
Classifier: Operating System :: Microsoft :: Windows
Classifier: Operating System :: POSIX :: Linux
Classifier: Programming Language :: Lua
Classifier: Programming Language :: Python
Classifier: Topic :: Games/Entertainment
Classifier: Topic :: Multimedia
Classifier: Topic :: Multimedia :: Sound/Audio
Classifier: Topic :: Multimedia :: Video
Requires-Dist: async-lru>=2.0.5
Requires-Dist: beautifulsoup4>=4.13.5
Requires-Dist: fuzzywuzzy>=0.18.0
Requires-Dist: httpx[http2]>=0.28.1
Requires-Dist: packaging>=25.0
Requires-Dist: platformdirs>=4.4.0
Requires-Dist: pypresence>=4.3.0
Requires-Dist: rich-argparse>=1.7.1
Requires-Dist: textual-image[textual]>=0.8.4
Requires-Dist: textual>=6.1.0
Requires-Dist: toml>=0.10.2
Provides-Extra: socks
Requires-Dist: httpx[socks]>=0.28.1; extra == 'socks'
Provides-Extra: speedups
Requires-Dist: levenshtein>=0.27.1; extra == 'speedups'
Requires-Dist: orjson>=3.11.3; extra == 'speedups'
